{"nodes": [{"id": "examples_readme", "label": "Examples README (reference fixtures)", "file_type": "document", "source_file": "examples/README.md", "source_location": null, "source_url": null, "captured_at": null, "author": null, "contributor": null}], "edges": [{"source": "examples_readme", "target": "examples_article_digest", "relation": "references", "confidence": "EXTRACTED", "confidence_score": 1.0, "source_file": "examples/README.md", "source_location": null, "weight": 1.0}, {"source": "examples_readme", "target": "examples_ats_normalization", "relation": "references", "confidence": "EXTRACTED", "confidence_score": 1.0, "source_file": "examples/README.md", "source_location": null, "weight": 1.0}, {"source": "examples_readme", "target": "examples_cv_example", "relation": "references", "confidence": "EXTRACTED", "confidence_score": 1.0, "source_file": "examples/README.md", "source_location": null, "weight": 1.0}, {"source": "examples_readme", "target": "examples_sample_report", "relation": "references", "confidence": "EXTRACTED", "confidence_score": 1.0, "source_file": "examples/README.md", "source_location": null, "weight": 1.0}, {"source": "examples_readme", "target": "examples_dual_track_readme", "relation": "references", "confidence": "EXTRACTED", "confidence_score": 1.0, "source_file": "examples/README.md", "source_location": null, "weight": 1.0}], "hyperedges": []}